MANIFEST.in
README.md
setup.cfg
setup.py
mongomonkey/__init__.py
mongomonkey/data.py
mongomonkey/fields.py
mongomonkey/model.py
mongomonkey/model_manager.py
mongomonkey/utils.py
mongomonkey.egg-info/PKG-INFO
mongomonkey.egg-info/SOURCES.txt
mongomonkey.egg-info/dependency_links.txt
mongomonkey.egg-info/requires.txt
mongomonkey.egg-info/top_level.txt