Metadata-Version: 1.0
Name: mongomonkey
Version: 0.1
Summary: A MongoDB object-document mapping layer for Python
Home-page: http://github.com/xonatius/mongo-monkey
Author: Daniil Bondarev
Author-email: xonatius@gmail.com
License: BSD
Keywords: mongo mongodb pymongo odm orm
Platform: UNKNOWN
